{
  "Infrastructures|Server / A cupboard or a dedicated room": [
    {
      "type": "g",
      "name" : "Have you led or are you planning actions to optimize your infrastructure? Especially :"
    },
    {
      "type": "sh",
      "name" : "Suspending network equipment",
      "answers": [
        "No",
        "I don't know",
        "Yes"
        ]
    },
    {
      "type": "sh",
      "name" : "Pooling physical equipment",
      "answers": [
        "No",
        "I don't know",
        "Yes"
        ]
    },
    {
      "type": "sh",
      "name" : "Uninstalling unnecessary infrastructure",
      "answers": [
        "No",
        "I don't know",
        "Yes"
        ]
    },
    {
      "type": "sh",
      "name" : "Traceability of material elements (CMDB)",
      "answers": [
        "No",
        "I don't know",
        "Yes"
        ]
    },
    {
      "type": "sh",
      "name" : "The correct sizing of the servers in relation to their use",
      "answers": [
        "No",
        "I don't know",
        "Yes"
        ]
    },
    {
      "type": "sh",
      "name" : "Give priority to ASHRAE 2 compatible equipment",
      "answers": [
        "No",
        "I don't know",
        "Yes"
        ]
    },
    {
      "type": "sh",
      "name" : "A procedure for provisioning and de-provisioning data-processing equipment in datacenters",
      "answers": [
        "No",
        "I don't know",
        "Yes"
        ]
    },
    {
      "type": "t",
      "name" : "How many physical servers do you have?",
      "answers": [
        "_"
        ]
    },
    {
      "type": "t",
      "name" : "How many virtual servers do you have?",
      "answers": [
        "_"
        ]
    },
    {
      "type": "st",
      "name" : "What will be the evolution of your number of physical servers for 2019? (in% or quantity)",
      "answers": [
        "In %_",
        "In quanity_",
        "I do not want to answer",
        "I don't know"
        ]
    },
    {
      "type": "st",
      "name" : "What will be the evolution of your number of virtual servers for 2019? (in% or quantity)",
      "answers": [
        "In %_",
        "In quanity_",
        "I do not want to answer",
        "I don't know"
        ]
    }

  ]
}
